MANIFEST.in
README.md
requirements.txt
setup.py
swiftbackmeup/__init__.py
swiftbackmeup/configuration.py
swiftbackmeup/exceptions.py
swiftbackmeup/lists.py
swiftbackmeup/parser.py
swiftbackmeup/shell.py
swiftbackmeup/utils.py
swiftbackmeup/version.py
swiftbackmeup.egg-info/PKG-INFO
swiftbackmeup.egg-info/SOURCES.txt
swiftbackmeup.egg-info/dependency_links.txt
swiftbackmeup.egg-info/entry_points.txt
swiftbackmeup.egg-info/requires.txt
swiftbackmeup.egg-info/top_level.txt
swiftbackmeup/items/__init__.py
swiftbackmeup/items/databases/__init__.py
swiftbackmeup/items/databases/mariadb.py
swiftbackmeup/items/databases/postgresql.py
swiftbackmeup/items/filesystems/__init__.py
swiftbackmeup/items/filesystems/file.py
swiftbackmeup/items/filesystems/git.py
swiftbackmeup/stores/__init__.py
swiftbackmeup/stores/swift.py