Metadata-Version: 1.1
Name: swiftbackmeup
Version: 0.0.5
Summary: Tools to backup databases to OpenStack Object Store Swift
Home-page: https://github.com/redhat-cip/swiftbackmeup
Author: Yanis Guenane
Author-email: yguenane@redhat.com
License: Apache v2.0
Platform: UNKNOWN
Classifier: Environment :: Console
Classifier: Intended Audience :: Developers
Classifier: Intended Audience :: Information Technology
Classifier: License :: OSI Approved :: Apache Software License
Classifier: Operating System :: POSIX :: Linux
Classifier: Programming Language :: Python :: 2.7
Classifier: Programming Language :: Python :: 3.4
